minimocker/__init__.py
minimocker/cli.py
minimocker/config_loader.py
minimocker/jwt_mock.py
minimocker/server.py
minimocker/utils.py
minimocker-0.1.0.dist-info/METADATA
minimocker-0.1.0.dist-info/WHEEL
minimocker-0.1.0.dist-info/entry_points.txt
minimocker-0.1.0.dist-info/top_level.txt
minimocker-0.1.0.dist-info/RECORD
