Metadata-Version: 2.4
Name: minimocker
Version: 0.1.0
Summary: A simple, reloadable API mock server with JWT support
Home-page: https://github.com/ramsawasthi/minimocker
Author: Ram Awasthi
Author-email: ram@skillsetpro.ai
License: MIT
Project-URL: Documentation, https://github.com/ramsawasthi/minimocker
Project-URL: Source, https://github.com/ramsawasthi/minimocker
Project-URL: Tracker, https://github.com/ramsawasthi/minimocker/issues
Classifier: Programming Language :: Python :: 3
Classifier: License :: OSI Approved :: MIT License
Classifier: Operating System :: OS Independent
Requires-Python: >=3.8
Requires-Dist: fastapi
Requires-Dist: uvicorn
Requires-Dist: python-jose
Requires-Dist: pyyaml
Dynamic: author
Dynamic: author-email
Dynamic: classifier
Dynamic: description
Dynamic: description-content-type
Dynamic: home-page
Dynamic: license
Dynamic: project-url
Dynamic: requires-dist
Dynamic: requires-python
Dynamic: summary
